roast/__init__.py
roast/_static_version.py
roast/_version.py
roast/component/aie.py
roast/component/basebuild.py
roast/component/cardano.py
roast/component/host_serial.py
roast/component/hwflow.py
roast/component/petalinux.py
roast/component/usbrelay.py
roast/component/yocto.py
roast/component/bif/__init__.py
roast/component/bif/bifdata.yaml
roast/component/bif/generate.py
roast/component/board/boot.py
roast/component/board/sd.py
roast/component/board/target_board.py
roast/component/crosscompile/__init__.py
roast/component/crosscompile/cmake.py
roast/component/crosscompile/crosscompile.py
roast/component/osl/__init__.py
roast/component/osl/build_component.py
roast/component/osl/generate_dts.tcl
roast/component/osl/microblaze.scr
roast/component/osl/versal.scr
roast/component/osl/zynq.scr
roast/component/osl/zynqmp.scr
roast/component/xsct/__init__.py
roast/component/xsct/apps_config.tcl
roast/component/xsct/build_app.tcl
roast/component/xsct/build_plm.tcl
roast/component/xsct/buildapp.py
roast/component/xsct/config.yaml
roast/component/xsct/defconfig.yaml
roast/component/xsct/download_dependency.py
roast/component/xsct/scout_app.tcl
roast/component/xsct/utils.tcl
roast/component/xsct/xsct_map.py
roast/component/xsdb/__init__.py
roast/component/xsdb/procname.yaml
roast/component/xsdb/xsdb.py
roast/machines/ac701.py
roast/machines/k26starterkit.py
roast/machines/kc705.py
roast/machines/kcu105.py
roast/machines/microblaze.py
roast/machines/psx.py
roast/machines/som.py
roast/machines/somproduction.py
roast/machines/sp701.py
roast/machines/vck190.py
roast/machines/vck190_emmc.py
roast/machines/vck190_ospi.py
roast/machines/vck5000.py
roast/machines/vcu118.py
roast/machines/vek280_es1.py
roast/machines/versal.py
roast/machines/vhk158_es1.py
roast/machines/vmk180.py
roast/machines/vmk180_emmc.py
roast/machines/vmk180_ospi.py
roast/machines/vpk120.py
roast/machines/vpk120_es1.py
roast/machines/vpk180.py
roast/machines/zc702.py
roast/machines/zc706.py
roast_xilinx-5.0.0.dist-info/LICENSE
roast_xilinx-5.0.0.dist-info/METADATA
roast_xilinx-5.0.0.dist-info/WHEEL
roast_xilinx-5.0.0.dist-info/entry_points.txt
roast_xilinx-5.0.0.dist-info/top_level.txt
roast_xilinx-5.0.0.dist-info/RECORD
