Metadata-Version: 2.1
Name: roast-xilinx
Version: 5.0.0
Summary: Randomized Okaying Across System Topologies (ROAST) Python Framework
Home-page: https://github.com/Xilinx/roast
Author: Ching-Hwa Yu
Author-email: chinghwa@xilinx.com
License: MIT
Keywords: roast-xilinx
Platform: UNKNOWN
Classifier: Development Status :: 5 - Production/Stable
Classifier: Operating System :: POSIX :: Linux
Classifier: Programming Language :: Python :: 3.6
Classifier: Programming Language :: Python :: 3.7
Classifier: Programming Language :: Python :: 3.8
Classifier: Programming Language :: Python :: 3.9
Classifier: License :: OSI Approved :: MIT License
Requires-Python: >=3.6, <4
License-File: LICENSE
Requires-Dist: roast (>=5.0.0.dev5)
Provides-Extra: dev
Requires-Dist: pytest ; extra == 'dev'
Requires-Dist: pytest-mock ; extra == 'dev'
Requires-Dist: pytest-black ; extra == 'dev'
Requires-Dist: pytest-freezegun ; extra == 'dev'
Requires-Dist: miniver ; extra == 'dev'
Requires-Dist: coverage ; extra == 'dev'
